matt/__init__.py
matt/__main__.py
matt/defaults.py
matt/exitcodes.py
matt/termcolor_wrapper.py
matt-0.2.0.dist-info/LICENSE
matt-0.2.0.dist-info/WHEEL
matt-0.2.0.dist-info/METADATA
matt-0.2.0.dist-info/RECORD
