Metadata-Version: 2.1
Name: matt
Version: 0.2.0
Summary: A maths test
Home-page: https://codeberg.org/noisytoot/matt
License: GPL-3.0-or-later
Author: Noisytoot
Requires-Python: >=3.6,<4.0
Classifier: License :: OSI Approved :: GNU General Public License v3 or later (GPLv3+)
Classifier: Programming Language :: Python :: 3
Classifier: Programming Language :: Python :: 3.6
Classifier: Programming Language :: Python :: 3.7
Classifier: Programming Language :: Python :: 3.8
Requires-Dist: colorama (>=0.4.3,<0.5.0); sys_platform == "win32"
Requires-Dist: pyxdg (>=0.26,<0.27)
Requires-Dist: termcolor (>=1.1.0,<2.0.0)
Project-URL: Repository, https://codeberg.org/noisytoot/matt
